alu_4bit.v
module alu_4bit(
    input [3:0]A,
    input [3:0]B,
    input [3:0]op,
    output reg [3:0]result,
    output reg ZF
);
always @(*)
 begin
    case(op)
    4'b0000 : result = A+B;
    4'b0001 : result = A-B;
    4'b0010 : result = A&B;
    4'b0011 : result = A|B;
    4'b0100 : result = A^B;
    4'b0101 : result = ~A;
    4'b0110 : result = A+1;
    4'b0111 : result = A-1;
    4'b1000 : result = A<<1;
    4'b1001 : result = A>>1;
    4'b1010 : result = (A==B) ? 4'b0000 : 4'b0001;
    default result = 4'b0000;
    endcase
    ZF= (result == 4'b0000) ? 1'b1 : 1'b0;
end
endmodule

tb_alu_4bit.v
module tb_alu_4bit;
    reg [3:0] A, B, op;
    wire [3:0] result;
    wire ZF;

    alu_4bit uut (
        .A(A),
        .B(B),
        .op(op),
        .result(result),
        .ZF(ZF)
    );

    initial begin
        $dumpfile("alu.vcd");
        $dumpvars(0, tb_alu_4bit);

        A = 4'b0101; B = 4'b0011; op = 4'b0000; #10; 
        A = 4'b0101; B = 4'b0011; op = 4'b0001; #10; 
        A = 4'b1100; B = 4'b1010; op = 4'b0010; #10;
        A = 4'b1100; B = 4'b1010; op = 4'b0011; #10; 
        A = 4'b1010; B = 4'b1010; op = 4'b0100; #10;
        A = 4'b1010; B = 4'b0000; op = 4'b0101; #10; 
        A = 4'b0001; B = 4'b0000; op = 4'b0110; #10; 
        A = 4'b0011; B = 4'b0000; op = 4'b0111; #10; 
        A = 4'b0011; B = 4'b0000; op = 4'b1000; #10;
        A = 4'b1000; B = 4'b0000; op = 4'b1001; #10; 
        A = 4'b1010; B = 4'b1010; op = 4'b1010; #10; 
        A = 4'b1000; B = 4'b0001; op = 4'b1010; #10; 

        #20 $finish;
    end
endmodule

alu.vcd
$date
	Fri Jul 11 14:28:13 2025
$end
$version
	Icarus Verilog
$end
$timescale
	1s
$end
$scope module tb_alu_4bit $end
$var wire 4 ! result [3:0] $end
$var wire 1 " ZF $end
$var reg 4 # A [3:0] $end
$var reg 4 $ B [3:0] $end
$var reg 4 % op [3:0] $end
$scope module uut $end
$var wire 4 & A [3:0] $end
$var wire 4 ' B [3:0] $end
$var wire 4 ( op [3:0] $end
$var reg 1 " ZF $end
$var reg 4 ) result [3:0] $end
$upscope $end
$upscope $end
$enddefinitions $end
$comment Show the parameter values. $end
$dumpall
$end
#0
$dumpvars
b1000 )
b0 (
b11 '
b101 &
b0 %
b11 $
b101 #
0"
b1000 !
$end
#10
b10 !
b10 )
b1 %
b1 (
#20
b1000 !
b1000 )
b10 %
b10 (
b1010 $
b1010 '
b1100 #
b1100 &
#30
b1110 !
b1110 )
b11 %
b11 (
#40
1"
b0 !
b0 )
b100 %
b100 (
b1010 #
b1010 &
#50
0"
b101 !
b101 )
b101 %
b101 (
b0 $
b0 '
#60
b10 !
b10 )
b110 %
b110 (
b1 #
b1 &
#70
b111 %
b111 (
b11 #
b11 &
#80
b110 !
b110 )
b1000 %
b1000 (
#90
b100 !
b100 )
b1001 %
b1001 (
b1000 #
b1000 &
#100
1"
b0 !
b0 )
b1010 %
b1010 (
b1010 $
b1010 '
b1010 #
b1010 &
#110
0"
b1 !
b1 )
b1 $
b1 '
b1000 #
b1000 &
